vdst_toolbox/__init__.py
vdst_toolbox/visualizations/__init__.py
vdst_toolbox/visualizations/radar.py
vdst_python_toolbox-1.0.0.dist-info/METADATA
vdst_python_toolbox-1.0.0.dist-info/WHEEL
vdst_python_toolbox-1.0.0.dist-info/top_level.txt
vdst_python_toolbox-1.0.0.dist-info/RECORD
