Metadata-Version: 2.1
Name: vdst-python-toolbox
Version: 1.0.0
Summary: Python package for various tools that will be used by Vestel Team
Home-page: UNKNOWN
Author: Berkay Gokova
Author-email: berkaygokova@gmail.com
License: UNKNOWN
Keywords: python,first package
Platform: UNKNOWN
Classifier: Development Status :: 3 - Alpha
Classifier: Intended Audience :: Education
Classifier: Programming Language :: Python :: 2
Classifier: Programming Language :: Python :: 3
Classifier: Operating System :: MacOS :: MacOS X
Classifier: Operating System :: Microsoft :: Windows
Requires-Dist: pandas
Requires-Dist: numpy
Requires-Dist: matplotlib
